Prac-06/design.sv
`timescale 1ns / 1ps
//pass_out is the regfile being brought to top.sv
module simple_cpu( clk, rst, instruction);

    parameter DATA_WIDTH = 8; //8 bit wide data
    parameter ADDR_BITS = 5; //32 Addresses
    parameter INSTR_WIDTH =20; //20b instruction

    input [INSTR_WIDTH-1:0] instruction;
    input clk, rst;

  	//outputs regfile register to pass_out register
  output reg [4*DATA_WIDTH-1:0] pass_out;
  //outputs but confusing formatting 
  //use reg0-reg3 signals in viewer
  
   //smaller registers containing 8 bit values 
  reg [DATA_WIDTH-1:0] reg0;
  reg [DATA_WIDTH-1:0] reg1;
  reg [DATA_WIDTH-1:0] reg2;
  reg [DATA_WIDTH-1:0] reg3;
 	
  
    //Wires for connecting to data memory    
    wire [ADDR_BITS-1:0] addr_i;
    wire [DATA_WIDTH-1:0] data_in_i, data_out_i, result2_i ;
    wire wen_i; 
    
    //wire for connecting to the ALU
    wire [DATA_WIDTH-1:0]operand_a_i, operand_b_i, result1_i;
    wire [3:0]opcode_i;
    
   
    //Wire for connecting to CU
    wire [DATA_WIDTH-1:0]offset_i;
    wire sel1_i, sel3_i;
    wire [DATA_WIDTH-1:0] operand_1_i, operand_2_i;

    
    
    //Instantiating an alu1
    alu #(DATA_WIDTH) alu1 (clk, operand_a_i, operand_b_i, opcode_i, result1_i);
     
    //instantiation of data memory
    reg_mem  #(DATA_WIDTH,ADDR_BITS) data_memory(result1_i, data_in_i, wen_i, clk, data_out_i);
    
    //Instantiation of a CU
    CU  #(DATA_WIDTH,ADDR_BITS, INSTR_WIDTH) CU1(clk, rst, instruction, result2_i,
        operand_1_i, operand_2_i, offset_i, opcode_i, sel1_i, sel3_i, wen_i, pass_out);   
//pass_out instantiation by name
    
    //Connect CU to ALU
    assign operand_a_i = operand_1_i;
    assign operand_b_i = (sel3_i == 0) ? operand_2_i: (sel3_i == 1) ? offset_i : 8'bx;
    
    //Connect CU to Memory
    assign data_in_i = operand_2_i;
    
    //Connect datamem to CU
    assign result2_i = (sel1_i == 0) ? data_out_i : (sel1_i == 1) ? result1_i : 8'bx;  
    
  
 //Assigning outputs to register in cpu module 
  	assign reg0 = pass_out[7:0];
  	assign reg1 = pass_out[15:8];
  	assign reg2 = pass_out[23:16];
  	assign reg3 = pass_out[31:24];
    

endmodule






//ALU 

module alu( clk, operand_a, operand_b, opcode, result);
    parameter DATA_WIDTH = 8;

    input clk;
    input[DATA_WIDTH-1:0]operand_a,operand_b;
    input [3:0] opcode;
    output reg[DATA_WIDTH-1:0] result;
    
  always@(posedge clk)
    begin
     case(opcode)
        4'b0000: //Addition
           result <= operand_a + operand_b ; 
        4'b0001: //Subtraction 
           result <= operand_a - operand_b;
        default: result <= 8'bx; 
     endcase
     
    end
endmodule

/*************************************************************************/

//RegMem

//`timescale 1ns / 1ps

module reg_mem (addr, data_in, wen, clk, data_out);

    parameter DATA_WIDTH = 8; //8 bit wide data
    parameter ADDR_BITS = 5; //32 Addresses

    input [ADDR_BITS-1:0] addr;
    input [DATA_WIDTH-1:0] data_in;
    input wen;
    input clk;
    output [DATA_WIDTH-1:0] data_out;

    reg [DATA_WIDTH-1:0] data_out;

    //8 memory locations each storing a 4bits wide value
    reg [DATA_WIDTH-1:0] mem_array [(2**ADDR_BITS)-1:0];

    always @(posedge clk) begin

        if (wen) begin //Write
            mem_array [addr] <= data_in;
            data_out <= #(DATA_WIDTH)'b0;
        end

        else begin //Read
            data_out <= mem_array[addr];
        end
    end

endmodule

/*************************************************************************/


//CU

//`timescale 1ns / 1ps
//pass_out defined to bring regfile to top cpu module
module CU (clk,rst, instr, result2, operand1, operand2, offset, opcode, sel1, sel3,w_r, pass_out);
    //Defaults unless overwritten during instantiation
    parameter DATA_WIDTH = 8; //8 bit wide data
    parameter ADDR_BITS = 5; //32 Addresses
    parameter INSTR_WIDTH =20; 
    //INPUTS
    input clk,rst;
    input [INSTR_WIDTH-1:0]instr;
    input [DATA_WIDTH-1:0] result2;

    //OUTPUTS
    output reg [DATA_WIDTH-1:0] operand1;
    output reg [DATA_WIDTH-1:0] operand2;
    output reg [DATA_WIDTH-1:0] offset;
    output reg [3:0] opcode;
    output reg sel1, sel3, w_r;
  output reg [4*DATA_WIDTH-1:0] pass_out;  //pass_out register for regfile
  
    //REGISTER FILE: CU internal register file of 4 registers.  This is a over simplication of a real solution
    reg [DATA_WIDTH-1:0] regfile [0:3];
    reg [INSTR_WIDTH-1:0]instruction;
    
    //STATES
    parameter RESET = 4'b0000;
    parameter DECODE = 4'b0001;
    parameter EXECUTE = 4'b0010;
    parameter MEM_ACCESS = 4'b0100;
    parameter WRITE_BACK = 4'b1000;
        
    reg [3:0] state = RESET;
    
  assign pass_out = {regfile[3],regfile[2],regfile[1],regfile[0]};  
    
    always @(posedge clk) begin
        instruction = instr;
        case (state)
            RESET : begin //#0
                if (instruction[19:18] == 2'b00)  begin
                    state = RESET; 
                    end else begin
                    state = DECODE; //#1
                    end
                //-----------------------------
                //Write initial values to regfile
                regfile[0]<= 8'd0;
                regfile[1]<= 8'd1;
                regfile[2]<= 8'd2;
                regfile[3]<= 8'd3;

                //Set output reset defaults
                operand1 <= #(DATA_WIDTH)'d0;
                operand2 <= #(DATA_WIDTH)'d0;
                offset <= #(DATA_WIDTH)'d0;
                opcode <= 4'b1111;
                sel1 <= 0;
                sel3 <= 0;
                w_r <= 0;
                //-----------------------------
            end

            DECODE : begin //#1
                state = EXECUTE; //#2
                if (instruction[19:18] == 2'b1) begin //std_op
                    operand1 <= regfile[instruction[15:14]]; //X2
                    operand2 <= regfile[instruction[13:12]]; //X3
                    offset <= instruction[11:4];
                    opcode <= instruction[3:0];
                   sel1 <= 1;
                    sel3 <= 0;
                    w_r <= 0;
                end else if (instruction[19:18] == 2'b10) begin //loadR 
                    operand1 <= regfile[instruction[15:14]]; //X2
                    operand2 <= regfile[instruction[17:16]]; //z
                    offset <= instruction[11:4];
                    opcode <= instruction[3:0];
                    sel1 <= 0; //pass data_out
                    sel3 <= 1; //pass offset
                    w_r <= 0;
                end else if (instruction[19:18] == 2'b11) begin //storeR 
                   /********************************************/ 

                  operand1 <= regfile[instruction[15:14]]; //X2
                    operand2 <= regfile[instruction[17:16]]; //X1
                    offset <= instruction[11:4];
                    opcode <= instruction[3:0];
                  
                  sel1 <= 0; //mux select to pass data_out 
                    sel3 <= 1; //mux select to pass offset into ALU
                    w_r <= 0; //write disable to memory 
                  
                   /********************************************/ 

                end
            end
            EXECUTE: begin //#2
                state = MEM_ACCESS; //#3
                if (instruction[19:18] == 2'b01) begin //std_op
                    state = WRITE_BACK;
                    operand1 <= regfile[instruction[15:14]]; //X2
                    operand2 <= regfile[instruction[13:12]]; //X3
                    offset <= instruction[11:4];
                    opcode <= instruction[3:0];
                    sel1 <= 1;
                    sel3 <= 0;
                    w_r <= 0;

                end else if (instruction[19:18] == 2'b10) begin //loadR  
                    operand1 <= regfile[instruction[15:14]]; //X2
                    operand2 <= regfile[instruction[17:16]]; //z
                    offset <= instruction[11:4];
                    opcode <= instruction[3:0];
                    sel1 <= 0; //pass data_out
                    sel3 <= 1; //pass offset
                    w_r <= 0;
                end else if (instruction[19:18] == 2'b11) begin //storeR
                   /********************************************/ 
                   operand1 <= regfile[instruction[15:14]]; //X2
                    operand2 <= regfile[instruction[17:16]]; //X1
                    offset <= instruction[11:4];
                    opcode <= instruction[3:0];
                  
                  sel1 <= 0; //mux select to pass data_out 
                    sel3 <= 1; //mux select to pass offset into ALU
                    w_r <= 1; //write enable for succeeding memory  
                   //access that will happen next 
                   /********************************************/ 
                end
            end
            MEM_ACCESS: begin //#3
                state = WRITE_BACK; //#4
                if (instruction[19:18] == 2'b10) begin //loadR             
                    operand1 <= regfile[instruction[15:14]]; //X2
                    operand2 <= regfile[instruction[17:16]]; //z
                    offset <= instruction[11:4];
                    opcode <= instruction[3:0];
                    sel1 <= 0; //mux select to pass data_out 
                    sel3 <= 1; //mux select to pass offset into ALU
                    w_r <= 0;
                end else if (instruction[19:18] == 2'b11) begin //storeR 
                   /********************************************/ 
                   
                  state = DECODE; //for FSM complacency
                  
                    operand1 <= regfile[instruction[15:14]]; //X2
                    operand2 <= regfile[instruction[17:16]]; //X1
                    offset <= instruction[11:4];
                    opcode <= instruction[3:0];
                  
                  	 sel1 <= 0; //mux select to pass data_out 
                    sel3 <= 1; //mux select to pass offset into ALU
                    w_r <= 0; //write disable to memory 
                   
                   /********************************************/ 
                end
            end
            WRITE_BACK: begin //#4
                state = DECODE; //#1
                if (instruction[19:18] == 2'b01) begin //std_op
                    regfile[instruction[17:16]] <= result2; //X1

                    operand1 <= regfile[instruction[15:14]]; //X2
                    operand2 <= regfile[instruction[13:12]]; //X3
                    offset <= instruction[11:4];
                    opcode <= instruction[3:0];
                    sel1 <= 1;
                    sel3 <= 0;
                    w_r <= 0;
                end else if (instruction[19:18] == 2'b11) begin //storeR 
                   /********************************************/ 
                  regfile[instruction[17:16]] <= result2; //X1
                  
                   operand1 <= regfile[instruction[15:14]]; //X2
                    operand2 <= regfile[instruction[17:16]]; //X1
                    offset <= instruction[11:4];
                    opcode <= instruction[3:0];
                  
                  	 sel1 <= 0; //mux select to pass data_out 
                    sel3 <= 1; //mux select to pass offset into ALU
                    w_r <= 0; //write disable to memory 
                   
                   /********************************************/ 
                    
                end else if (instruction[19:18] == 2'b10) begin //loadR             
                    regfile[instruction[17:16]] <= result2; //From data mem
                    operand1 <= regfile[instruction[15:14]]; //X2
                    operand2 <= regfile[instruction[17:16]]; //z
                    offset <= instruction[11:4];
                    opcode <= instruction[3:0];
                    sel1 <= 0; //pass data_out
                    sel3 <= 1; //pass offset
                    w_r <= 0; //write disable to memory
                end
            end

            default: // Fault Recovery
            state = RESET; //#0
        endcase
    end
endmodule

Prac-06/testbench.sv
`timescale 1ns / 1ps
 
module tb_simple_CPU;
       
    parameter DATA_WIDTH = 8; //8 bit wide data
    parameter ADDR_BITS = 5; //32 Addresses
    parameter INSTR_WIDTH =20; //20b instruction
   
    reg clk, rst;
    reg [INSTR_WIDTH-1:0] instruction;
  //reg [4*DATA_WIDTH-1:0] pass_out; //failed attempt at passing regfile up
    
  simple_cpu  #(DATA_WIDTH,ADDR_BITS,INSTR_WIDTH) SCPU_DUT(clk, rst, instruction);
    
    initial begin
      
      $dumpfile("dump.vcd");
        $dumpvars();
      
        clk = 1'b1;
        rst = 1'b1;
        instruction = 20'd0;
        repeat(3) #1 clk=!clk;
        rst = 1'b0;
        repeat(2) #1 clk=!clk;
                
                
        /*Info on the simple CPU:
            * Reset sets regfile = [0,1,2,3]
            * ADD = opcode 0, SUB = opcode 1  
        */
            
                                        //ADD:    reg0  = reg1 + reg3   //1+3=4
        //In the instruction this is:    (instr)  (X1)    (X2)   (X3)  
        instruction = 20'b01000111000000000000;
        repeat(8) #1 clk=!clk; //4 rising edges
        
                                        //ADD:    reg1  = reg0 + reg3   //4+3=7
        //In the instruction this is:    (instr)  (X1)    (X2)   (X3)
        instruction = 20'b01010011000000000000;
        repeat(6) #1 clk=!clk; 
                
                                         //SUB:   reg3  = reg0 - reg2  //4-2=2  
       //In the instruction this is:    (instr)  (X1)    (X2)   (X3) 
        instruction = 20'b01110010000000000001;
        repeat(6) #1 clk=!clk;
        
                                         //STORE_R:   DATA_MEM(reg2 + 15) = reg1  //DATA_MEM(2+15)=7  
        //In the instruction this is:    (instr)               (X2)         (X1)
        instruction = 20'b11011000000011110000;
        repeat(6) #1 clk=!clk;
        
                                           //STORE_R:   DATA_MEM(reg3 + 22) = reg0  //DATA_MEM(2+22)= 4  
        //In the instruction this is:    (instr)                 (X2)         (X1)
        instruction = 20'b11001100000101100000;
        repeat(6) #1 clk=!clk;

                                           //LOAD_R:   DATA_MEM(reg2 + 15) = reg3  //reg3 = DATA_MEM(2+15)  -> reg3 becomes 7  
        //In the instruction this is:    (instr)                (X2)         (X1)
        instruction = 20'b10111000000011110000;
        repeat(7) #1 clk=!clk;
        
//2nd Load_R instruction
      
                                                //LOAD_R:   DATA_MEM(reg2 + 15) = reg3  //reg3 = DATA_MEM(2+15)  -> reg3 becomes 7  
        //In the instruction this is:    (instr)                (X2)         (X1)
        instruction = 20'b10111000000011110000;
        repeat(7) #1 clk=!clk;
        
    end
    
    
endmodule

Prac-06/result/dump.vcd
$date
	Thu Nov  4 18:59:22 2021
$end
$version
	Icarus Verilog
$end
$timescale
	1ps
$end
$scope module tb_simple_CPU $end
$var reg 1 ! clk $end
$var reg 20 " instruction [19:0] $end
$var reg 1 # rst $end
$scope module SCPU_DUT $end
$var wire 1 ! clk $end
$var wire 8 $ data_in_i [7:0] $end
$var wire 20 % instruction [19:0] $end
$var wire 8 & operand_a_i [7:0] $end
$var wire 1 # rst $end
$var wire 1 ' wen_i $end
$var wire 1 ( sel3_i $end
$var wire 1 ) sel1_i $end
$var wire 8 * result2_i [7:0] $end
$var wire 8 + result1_i [7:0] $end
$var wire 8 , reg3 [7:0] $end
$var wire 8 - reg2 [7:0] $end
$var wire 8 . reg1 [7:0] $end
$var wire 8 / reg0 [7:0] $end
$var wire 32 0 pass_out [31:0] $end
$var wire 8 1 operand_b_i [7:0] $end
$var wire 8 2 operand_2_i [7:0] $end
$var wire 8 3 operand_1_i [7:0] $end
$var wire 4 4 opcode_i [3:0] $end
$var wire 8 5 offset_i [7:0] $end
$var wire 8 6 data_out_i [7:0] $end
$scope module CU1 $end
$var wire 1 ! clk $end
$var wire 20 7 instr [19:0] $end
$var wire 8 8 result2 [7:0] $end
$var wire 1 # rst $end
$var wire 32 9 pass_out [31:0] $end
$var reg 20 : instruction [19:0] $end
$var reg 8 ; offset [7:0] $end
$var reg 4 < opcode [3:0] $end
$var reg 8 = operand1 [7:0] $end
$var reg 8 > operand2 [7:0] $end
$var reg 1 ) sel1 $end
$var reg 1 ( sel3 $end
$var reg 4 ? state [3:0] $end
$var reg 1 ' w_r $end
$upscope $end
$scope module alu1 $end
$var wire 1 ! clk $end
$var wire 4 @ opcode [3:0] $end
$var wire 8 A operand_a [7:0] $end
$var wire 8 B operand_b [7:0] $end
$var reg 8 C result [7:0] $end
$upscope $end
$scope module data_memory $end
$var wire 5 D addr [4:0] $end
$var wire 1 ! clk $end
$var wire 8 E data_in [7:0] $end
$var wire 1 ' wen $end
$var reg 8 F data_out [7:0] $end
$upscope $end
$upscope $end
$upscope $end
$enddefinitions $end
#0
$dumpvars
bx F
bx E
bx D
bx C
bx B
bx A
b1111 @
b0 ?
bx >
bx =
b1111 <
bx ;
b0 :
b11000000100000000100000000 9
bx 8
b0 7
bx 6
bx 5
b1111 4
bx 3
bx 2
bx 1
b11000000100000000100000000 0
b0 /
b1 .
b10 -
b11 ,
bx +
bx *
0)
0(
0'
bx &
b0 %
bx $
1#
b0 "
1!
$end
#1000
0!
#2000
1!
#3000
0#
0!
#4000
1!
#5000
b1000111000000000000 "
b1000111000000000000 %
b1000111000000000000 7
0!
#6000
b1 ?
b1000111000000000000 :
1!
#7000
0!
#8000
b11 1
b11 B
1)
b0 4
b0 <
b0 @
b0 5
b0 ;
b11 $
b11 E
b11 2
b11 >
b1 &
b1 A
b1 3
b1 =
b10 ?
1!
#9000
0!
#10000
b100 *
b100 8
b100 D
b100 +
b100 C
b11 $
b11 E
b11 2
b11 >
b1 &
b1 A
b1 3
b1 =
b1000 ?
1!
#11000
0!
#12000
b100 /
b11000000100000000100000100 0
b11000000100000000100000100 9
b11 $
b11 E
b11 2
b11 >
b1 &
b1 A
b1 3
b1 =
b1 ?
1!
#13000
b1010011000000000000 "
b1010011000000000000 %
b1010011000000000000 7
0!
#14000
b11 $
b11 E
b11 2
b11 >
b100 &
b100 A
b100 3
b100 =
b10 ?
b1010011000000000000 :
1!
#15000
0!
#16000
b111 *
b111 8
b111 D
b111 +
b111 C
b1000 ?
1!
#17000
0!
#18000
b111 .
b11000000100000011100000100 0
b11000000100000011100000100 9
b1 ?
1!
#19000
b1110010000000000001 "
b1110010000000000001 %
b1110010000000000001 7
0!
#20000
b10 1
b10 B
b1 4
b1 <
b1 @
b10 $
b10 E
b10 2
b10 >
b10 ?
b1110010000000000001 :
1!
#21000
0!
#22000
b10 *
b10 8
b10 D
b10 +
b10 C
b1000 ?
1!
#23000
0!
#24000
b10 ,
b10000000100000011100000100 0
b10000000100000011100000100 9
b1 ?
1!
#25000
b11011000000011110000 "
b11011000000011110000 %
b11011000000011110000 7
0!
#26000
bx *
bx 8
b1111 1
b1111 B
1(
0)
b0 4
b0 <
b0 @
b1111 5
b1111 ;
b111 $
b111 E
b111 2
b111 >
b10 &
b10 A
b10 3
b10 =
b10 ?
b11011000000011110000 :
1!
#27000
0!
#28000
b10001 D
b10001 +
b10001 C
1'
b100 ?
1!
#29000
0!
#30000
0'
b1 ?
1!
#31000
b11001100000101100000 "
b11001100000101100000 %
b11001100000101100000 7
0!
#32000
b10110 1
b10110 B
b111 *
b111 8
b111 6
b111 F
b10110 5
b10110 ;
b100 $
b100 E
b100 2
b100 >
b10 ?
b11001100000101100000 :
1!
#33000
0!
#34000
b11000 D
1'
b11000 +
b11000 C
b100 ?
1!
#35000
0!
#36000
0'
b1 ?
1!
#37000
b10111000000011110000 "
b10111000000011110000 %
b10111000000011110000 7
0!
#38000
b1111 1
b1111 B
b100 *
b100 8
b1111 5
b1111 ;
b10 $
b10 E
b10 2
b10 >
b100 6
b100 F
b10 ?
b10111000000011110000 :
1!
#39000
0!
#40000
b10001 D
b10001 +
b10001 C
b100 ?
1!
#41000
0!
#42000
b111 *
b111 8
b111 6
b111 F
b1000 ?
1!
#43000
0!
#44000
b111 ,
b111000000100000011100000100 0
b111000000100000011100000100 9
b111 6
b111 F
b1 ?
1!
#45000
0!
#46000
b111 $
b111 E
b111 2
b111 >
b10 ?
1!
#47000
0!
#48000
b100 ?
1!
#49000
0!
#50000
b1000 ?
1!
